dl_sh_source.py
dl_sh_source-0.4.dist-info/METADATA
dl_sh_source-0.4.dist-info/WHEEL
dl_sh_source-0.4.dist-info/entry_points.txt
dl_sh_source-0.4.dist-info/licenses/LICENSE
dl_sh_source-0.4.dist-info/RECORD
