Metadata-Version: 2.4
Name: dl-sh-source
Version: 0.4
Summary: Download articles from Sci Hub given the article's DOI.
Project-URL: Homepage, https://codeberg.org/hyperreal/dl-sh-source
Project-URL: Issues, https://codeberg.org/hyperreal/dl-sh-source/issues
Author-email: Jeffrey Serio <hyperreal@fedoraproject.org>
License-File: LICENSE
Classifier: License :: OSI Approved :: GNU General Public License v3 or later (GPLv3+)
Classifier: Operating System :: OS Independent
Classifier: Programming Language :: Python :: 3
Requires-Python: >=3.10
Requires-Dist: beautifulsoup4>=4.12.3
Requires-Dist: requests>=2.32.3
